nonebot_plugin_bili_push/__init__.py
nonebot_plugin_bili_push-1.1.24.dist-info/LICENSE
nonebot_plugin_bili_push-1.1.24.dist-info/METADATA
nonebot_plugin_bili_push-1.1.24.dist-info/WHEEL
nonebot_plugin_bili_push-1.1.24.dist-info/top_level.txt
nonebot_plugin_bili_push-1.1.24.dist-info/RECORD
